easyswitch/__init__.py
easyswitch/client.py
easyswitch/exceptions.py
easyswitch/types.py
easyswitch/adapters/__init__.py
easyswitch/adapters/base.py
easyswitch/adapters/interfaces.py
easyswitch/conf/__init__.py
easyswitch/conf/base.py
easyswitch/conf/config.py
easyswitch/conf/manager.py
easyswitch/conf/sources/dict.py
easyswitch/conf/sources/env.py
easyswitch/conf/sources/json.py
easyswitch/conf/sources/yaml.py
easyswitch/integrators/__init__.py
easyswitch/integrators/bizao.py
easyswitch/integrators/cinetpay.py
easyswitch/integrators/kkiapay.py
easyswitch/integrators/mtn.py
easyswitch/integrators/paydunya.py
easyswitch/integrators/paygate.py
easyswitch/integrators/payplus.py
easyswitch/integrators/qospay.py
easyswitch/integrators/semoa.py
easyswitch/integrators/fedapay/__init__.py
easyswitch/integrators/fedapay/types.py
easyswitch/integrators/fedapay/utils.py
easyswitch/utils/__init__.py
easyswitch/utils/http.py
easyswitch/utils/logger.py
easyswitch/utils/validators.py
easyswitch-0.1.3.dist-info/licenses/LICENSE
easyswitch-0.1.3.dist-info/METADATA
easyswitch-0.1.3.dist-info/WHEEL
easyswitch-0.1.3.dist-info/top_level.txt
easyswitch-0.1.3.dist-info/RECORD
