Metadata-Version: 2.4
Name: easyswitch
Version: 0.1.3
Summary: Unified Python SDK for Mobile money 
Home-page: https://github.com/AllDotPy/EasySwitch.git
Author: #Einswilli
Author-email: AllDotPy <hello@alldotpy.com>
Maintainer-email: #Einswilli <einswilligoeh@email.com>, Julien ADENOVI <adenovijulien@email.com>, Koffi Boris Gilbride WOGLO <wokobogil@gmail.com>
License: MIT License
Project-URL: Homepage, https://github.com/AllDotPy/EasySwitch
Project-URL: Repository, https://github.com/AllDotPy/EasySwitch
Project-URL: Documentation, https://alldotpy.github.io/EasySwitch
Project-URL: Tracker, https://github.com/AllDotPy/EasySwitch/issues
Classifier: Programming Language :: Python :: 3
Classifier: License :: OSI Approved :: MIT License
Classifier: Operating System :: OS Independent
Requires-Python: >=3.9
License-File: LICENSE
Requires-Dist: aiohttp>=3.11.18
Requires-Dist: phonenumbers>=9.0.5
Requires-Dist: pydantic>=2.11.4
Requires-Dist: python-dateutil>=2.9.0.post0
Requires-Dist: python-dotenv>=1.1.0
Requires-Dist: pyyaml>=6.0.2
Provides-Extra: dev
Requires-Dist: black; extra == "dev"
Requires-Dist: mypy; extra == "dev"
Requires-Dist: twine; extra == "dev"
Requires-Dist: uv; extra == "dev"
Requires-Dist: build; extra == "dev"
Requires-Dist: isort>=6.0.1; extra == "dev"
Requires-Dist: pytest>=8.4.0; extra == "dev"
Requires-Dist: pytest>=8.3.5; extra == "dev"
Requires-Dist: pytest-asyncio>=0.26.0; extra == "dev"
Requires-Dist: pytest-mock>=3.14.0; extra == "dev"
Requires-Dist: mkdocs>=1.6.1; extra == "dev"
Requires-Dist: mkdocs-material>=9.6.14; extra == "dev"
Requires-Dist: mkdocs-static-i18n>=1.3.0; extra == "dev"
Requires-Dist: setuptools>=80.8.0; extra == "dev"
Dynamic: author
Dynamic: home-page
Dynamic: license-file
